[
  {
    "activist_id": 379,
    "investor_id": 6040,
    "PID": 50092,
    "activist_name": "Citron Research",
    "campaign_summary_id": 31054,
    "company_id": 20280,
    "company_name": "Nano X Imaging Ltd.",
    "symbol": "NNOX",
    "action_date": "15-Sep-20",
    "action": "Stock Promotion",
    "exchange_name": "NASDAQ",
    "return": 29.120098,
    "class_action": "No",
    "auditor_resigned": "No",
    "full_report": "Yes",
    "delisted": "No",
    "company_respnd": "Yes",
    "current_status": "Current",
    "price_per_share": null,
    "Purchase_Value_mn": null,
    "currency": "",
    "buyer": "",
    "activist_founded": 2001,
    "market_cap_USD": 2197.737309,
    "industry_name": "Medical Devices",
    "industry_sector_name": "Healthcare",
    "country": "Israel",
    "Year_action": 2020,
    "company_region": "Asia",
    "market_cap_category": "Mid-Cap",
    "activist_HQ": "US",
    "exit_date": "11-May-21",
    "Downside_Target": 100
  },
  {
    "activist_id": 1931,
    "investor_id": 5935,
    "PID": 36738,
    "activist_name": "Viceroy Research",
    "campaign_summary_id": 31037,
    "company_id": 20270,
    "company_name": "GRENKE AG",
    "symbol": "GLJ.DE",
    "action_date": "15-Sep-20",
    "action": "Major Business Fraud",
    "exchange_name": "Deutsche Börse",
    "return": 38.601272,
    "class_action": "No",
    "auditor_resigned": "No",
    "full_report": "Yes",
    "delisted": "No",
    "company_respnd": "Yes",
    "current_status": "Current",
    "price_per_share": null,
    "Purchase_Value_mn": null,
    "currency": "",
    "buyer": "",
    "activist_founded": 2016,
    "market_cap_USD": 1689.307071,
    "industry_name": "Asset Management",
    "industry_sector_name": "Financial Services",
    "country": "Germany",
    "Year_action": 2020,
    "company_region": "Europe",
    "market_cap_category": "Small-Cap",
    "activist_HQ": "US",
    "exit_date": "11-May-21",
    "Downside_Target": null
  },
  {
    "activist_id": 4084,
    "investor_id": 9288,
    "PID": 46033,
    "activist_name": "Mariner Research",
    "campaign_summary_id": 31031,
    "company_id": 18889,
    "company_name": "AudioEye Inc",
    "symbol": "AEYE",
    "action_date": "14-Sep-20",
    "action": "Other Overvaluation, Product Ineffective",
    "exchange_name": "NASDAQ",
    "return": 4.402895,
    "class_action": "No",
    "auditor_resigned": "No",
    "full_report": "Yes",
    "delisted": "No",
    "company_respnd": "No",
    "current_status": "Current",
    "price_per_share": null,
    "Purchase_Value_mn": null,
    "currency": "",
    "buyer": "",
    "activist_founded": null,
    "market_cap_USD": 349.902869,
    "industry_name": "Software - Application",
    "industry_sector_name": "Technology",
    "country": "US",
    "Year_action": 2020,
    "company_region": "North America",
    "market_cap_category": "Small-Cap",
    "activist_HQ": null,
    "exit_date": "11-May-21",
    "Downside_Target": 45.2054
  },
  {
    "activist_id": 2738,
    "investor_id": 5486,
    "PID": 48418,
    "activist_name": "Hindenburg Research",
    "campaign_summary_id": 31010,
    "company_id": 19346,
    "company_name": "Nikola Corporation",
    "symbol": "NKLA",
    "action_date": "10-Sep-20",
    "action": "Major Business Fraud, Stock Promotion",
    "exchange_name": "NASDAQ",
    "return": 19.306113,
    "class_action": "No",
    "auditor_resigned": "No",
    "full_report": "Yes",
    "delisted": "No",
    "company_respnd": "Yes",
    "current_status": "Current",
    "price_per_share": null,
    "Purchase_Value_mn": null,
    "currency": "",
    "buyer": "",
    "activist_founded": 2017,
    "market_cap_USD": 7562.596435,
    "industry_name": "Auto Manufacturers",
    "industry_sector_name": "Consumer Cyclical",
    "country": "US",
    "Year_action": 2020,
    "company_region": "North America",
    "market_cap_category": "Mid-Cap",
    "activist_HQ": "US",
    "exit_date": "11-May-21",
    "Downside_Target": null
  },
  {
    "activist_id": 1967,
    "investor_id": 5981,
    "PID": 4209,
    "activist_name": "J Capital Research Limited",
    "campaign_summary_id": 30986,
    "company_id": 11841,
    "company_name": "Northern Dynasty Minerals, Ltd.",
    "symbol": "NAK",
    "action_date": "09-Sep-20",
    "action": "Product Ineffective",
    "exchange_name": "NYSE MKT",
    "return": -12.121212,
    "class_action": "No",
    "auditor_resigned": "No",
    "full_report": "Yes",
    "delisted": "No",
    "company_respnd": "Yes",
    "current_status": "Current",
    "price_per_share": null,
    "Purchase_Value_mn": null,
    "currency": "",
    "buyer": "",
    "activist_founded": 2011,
    "market_cap_USD": 371.524216,
    "industry_name": "Industrial Metals & Minerals",
    "industry_sector_name": "Basic Materials",
    "country": "Canada",
    "Year_action": 2020,
    "company_region": "North America",
    "market_cap_category": "Small-Cap",
    "activist_HQ": "US",
    "exit_date": "11-May-21",
    "Downside_Target": null
  },
  {
    "activist_id": 402,
    "investor_id": 6780,
    "PID": 3076,
    "activist_name": "Muddy Waters Research",
    "campaign_summary_id": 30969,
    "company_id": 5923,
    "company_name": "Inovio Pharmaceuticals Inc.",
    "symbol": "INO",
    "action_date": "02-Sep-20",
    "action": "Stock Promotion",
    "exchange_name": "NYSE",
    "return": -48.992112,
    "class_action": "No",
    "auditor_resigned": "No",
    "full_report": "No",
    "delisted": "No",
    "company_respnd": "No",
    "current_status": "Current",
    "price_per_share": null,
    "Purchase_Value_mn": null,
    "currency": "",
    "buyer": "",
    "activist_founded": 2010,
    "market_cap_USD": 1978.696874,
    "industry_name": "Biotechnology",
    "industry_sector_name": "Healthcare",
    "country": "US",
    "Year_action": 2020,
    "company_region": "North America",
    "market_cap_category": "Small-Cap",
    "activist_HQ": "US",
    "exit_date": "11-May-21",
    "Downside_Target": null
  },
  {
    "activist_id": 1269,
    "investor_id": 6517,
    "PID": 37412,
    "activist_name": "White Diamond Research",
    "campaign_summary_id": 30878,
    "company_id": 20155,
    "company_name": "Atomera Inc",
    "symbol": "ATOM",
    "action_date": "26-Aug-20",
    "action": "Product Ineffective, Bubble",
    "exchange_name": "NASDAQ",
    "return": 6.784141,
    "class_action": "No",
    "auditor_resigned": "No",
    "full_report": "Yes",
    "delisted": "No",
    "company_respnd": "No",
    "current_status": "Current",
    "price_per_share": null,
    "Purchase_Value_mn": null,
    "currency": "",
    "buyer": "",
    "activist_founded": 2009,
    "market_cap_USD": 704.469943,
    "industry_name": "Semiconductor Equipment & Materials",
    "industry_sector_name": "Technology",
    "country": "US",
    "Year_action": 2020,
    "company_region": "North America",
    "market_cap_category": "Small-Cap",
    "activist_HQ": "US",
    "exit_date": "11-May-21",
    "Downside_Target": 72.826
  },
  {
    "activist_id": 3722,
    "investor_id": 7996,
    "PID": 49600,
    "activist_name": "Grizzly Research LLC",
    "campaign_summary_id": 30871,
    "company_id": 20142,
    "company_name": "LexinFintech Holdings Ltd.",
    "symbol": "LX",
    "action_date": "25-Aug-20",
    "action": "Over-Levered",
    "exchange_name": "NASDAQ",
    "return": 19.623972,
    "class_action": "No",
    "auditor_resigned": "No",
    "full_report": "Yes",
    "delisted": "No",
    "company_respnd": "No",
    "current_status": "Current",
    "price_per_share": null,
    "Purchase_Value_mn": null,
    "currency": "",
    "buyer": "",
    "activist_founded": null,
    "market_cap_USD": 1633.03283,
    "industry_name": "Credit Services",
    "industry_sector_name": "Financial Services",
    "country": null,
    "Year_action": 2020,
    "company_region": null,
    "market_cap_category": "Small-Cap",
    "activist_HQ": "US",
    "exit_date": "11-May-21",
    "Downside_Target": 100
  },
  {
    "activist_id": 379,
    "investor_id": 6040,
    "PID": 4817,
    "activist_name": "Citron Research",
    "campaign_summary_id": 30900,
    "company_id": 5808,
    "company_name": "Plug Power Inc.",
    "symbol": "PLUG",
    "action_date": "21-Aug-20",
    "action": "Upcoming Earnings Miss",
    "exchange_name": "NASDAQ",
    "return": 0.804682,
    "class_action": "No",
    "auditor_resigned": "No",
    "full_report": "No",
    "delisted": "No",
    "company_respnd": "No",
    "current_status": "Current",
    "price_per_share": null,
    "Purchase_Value_mn": null,
    "currency": "",
    "buyer": "",
    "activist_founded": 2001,
    "market_cap_USD": 21801.667874,
    "industry_name": "Electronic Components",
    "industry_sector_name": "Technology",
    "country": "US",
    "Year_action": 2020,
    "company_region": "North America",
    "market_cap_category": "Large-Cap",
    "activist_HQ": "US",
    "exit_date": "11-May-21",
    "Downside_Target": 45.8623
  },
  {
    "activist_id": 2738,
    "investor_id": 5486,
    "PID": 42369,
    "activist_name": "Hindenburg Research",
    "campaign_summary_id": 30858,
    "company_id": 20131,
    "company_name": "GrowGeneration Corp",
    "symbol": "GRWG",
    "action_date": "21-Aug-20",
    "action": "Bubble, Other Illegal",
    "exchange_name": "NASDAQ",
    "return": 12.445175,
    "class_action": "No",
    "auditor_resigned": "No",
    "full_report": "Yes",
    "delisted": "No",
    "company_respnd": "Yes",
    "current_status": "Current",
    "price_per_share": null,
    "Purchase_Value_mn": null,
    "currency": "",
    "buyer": "",
    "activist_founded": 2017,
    "market_cap_USD": 2484.761031,
    "industry_name": "Industrial Distribution",
    "industry_sector_name": "Industrials",
    "country": "US",
    "Year_action": 2020,
    "company_region": "North America",
    "market_cap_category": "Mid-Cap",
    "activist_HQ": "US",
    "exit_date": "11-May-21",
    "Downside_Target": 57.9129
  },
  {
    "activist_id": 3808,
    "investor_id": 8572,
    "PID": 43993,
    "activist_name": "Culper Research",
    "campaign_summary_id": 30844,
    "company_id": 20111,
    "company_name": "Blink Charging Co",
    "symbol": "BLNK",
    "action_date": "19-Aug-20",
    "action": "Stock Promotion",
    "exchange_name": "NASDAQ",
    "return": 17.986315,
    "class_action": "No",
    "auditor_resigned": "No",
    "full_report": "Yes",
    "delisted": "No",
    "company_respnd": "Yes",
    "current_status": "Current",
    "price_per_share": null,
    "Purchase_Value_mn": null,
    "currency": "",
    "buyer": "",
    "activist_founded": 2018,
    "market_cap_USD": 1252.573592,
    "industry_name": "Business Services",
    "industry_sector_name": "Industrials",
    "country": "US",
    "Year_action": 2020,
    "company_region": "North America",
    "market_cap_category": "Small-Cap",
    "activist_HQ": "US",
    "exit_date": "11-May-21",
    "Downside_Target": null
  },
  {
    "activist_id": 4084,
    "investor_id": 9288,
    "PID": 43993,
    "activist_name": "Mariner Research",
    "campaign_summary_id": 30847,
    "company_id": 20111,
    "company_name": "Blink Charging Co",
    "symbol": "BLNK",
    "action_date": "19-Aug-20",
    "action": "Product Ineffective, Bubble, Stock Promotion",
    "exchange_name": "NASDAQ",
    "return": 17.986315,
    "class_action": "No",
    "auditor_resigned": "No",
    "full_report": "Yes",
    "delisted": "No",
    "company_respnd": "Yes",
    "current_status": "Current",
    "price_per_share": null,
    "Purchase_Value_mn": null,
    "currency": "",
    "buyer": "",
    "activist_founded": null,
    "market_cap_USD": 1252.573592,
    "industry_name": "Business Services",
    "industry_sector_name": "Industrials",
    "country": "US",
    "Year_action": 2020,
    "company_region": "North America",
    "market_cap_category": "Small-Cap",
    "activist_HQ": null,
    "exit_date": "11-May-21",
    "Downside_Target": 89.4179
  },
  {
    "activist_id": 407,
    "investor_id": 6027,
    "PID": 49565,
    "activist_name": "Spruce Point Capital Management",
    "campaign_summary_id": 30823,
    "company_id": 20100,
    "company_name": "GFL Environmental Inc.",
    "symbol": "GFL",
    "action_date": "18-Aug-20",
    "action": "Ineffective Roll-Up",
    "exchange_name": "NYSE",
    "return": -5.652379,
    "class_action": "No",
    "auditor_resigned": "No",
    "full_report": "Yes",
    "delisted": "No",
    "company_respnd": "Yes",
    "current_status": "Current",
    "price_per_share": null,
    "Purchase_Value_mn": null,
    "currency": "",
    "buyer": "",
    "activist_founded": 2009,
    "market_cap_USD": 9515.826546,
    "industry_name": "Waste Management",
    "industry_sector_name": "Industrials",
    "country": null,
    "Year_action": 2020,
    "company_region": null,
    "market_cap_category": "Mid-Cap",
    "activist_HQ": "US",
    "exit_date": "11-May-21",
    "Downside_Target": 100
  },
  {
    "activist_id": 1967,
    "investor_id": 5981,
    "PID": 2937,
    "activist_name": "J Capital Research Limited",
    "campaign_summary_id": 30743,
    "company_id": 3449,
    "company_name": "STAAR Surgical Company",
    "symbol": "STAA",
    "action_date": "11-Aug-20",
    "action": "Accounting Fraud",
    "exchange_name": "NASDAQ",
    "return": -8.809802,
    "class_action": "No",
    "auditor_resigned": "No",
    "full_report": "Yes",
    "delisted": "No",
    "company_respnd": "No",
    "current_status": "Current",
    "price_per_share": null,
    "Purchase_Value_mn": null,
    "currency": "",
    "buyer": "",
    "activist_founded": 2011,
    "market_cap_USD": 5120.489403,
    "industry_name": "Medical Instruments & Supplies",
    "industry_sector_name": "Healthcare",
    "country": "US",
    "Year_action": 2020,
    "company_region": "North America",
    "market_cap_category": "Mid-Cap",
    "activist_HQ": "US",
    "exit_date": "11-May-21",
    "Downside_Target": null
  },
  {
    "activist_id": 4252,
    "investor_id": 11060,
    "PID": 31656,
    "activist_name": "Lighthaven Capital Management LLC",
    "campaign_summary_id": 30746,
    "company_id": 11539,
    "company_name": "Energous Corp",
    "symbol": "WATT",
    "action_date": "11-Aug-20",
    "action": "Product Ineffective",
    "exchange_name": "NASDAQ",
    "return": 3.636364,
    "class_action": "No",
    "auditor_resigned": "No",
    "full_report": "Yes",
    "delisted": "No",
    "company_respnd": "No",
    "current_status": "Current",
    "price_per_share": null,
    "Purchase_Value_mn": null,
    "currency": "",
    "buyer": "",
    "activist_founded": 2011,
    "market_cap_USD": 215.160696,
    "industry_name": "Electronic Components",
    "industry_sector_name": "Technology",
    "country": "US",
    "Year_action": 2020,
    "company_region": "North America",
    "market_cap_category": "Micro-Cap",
    "activist_HQ": "US",
    "exit_date": "11-May-21",
    "Downside_Target": null
  },
  {
    "activist_id": 3733,
    "investor_id": 8006,
    "PID": 5166,
    "activist_name": "Wolfpack Research",
    "campaign_summary_id": 30753,
    "company_id": 15024,
    "company_name": "Remark Holdings Inc",
    "symbol": "MARK",
    "action_date": "11-Aug-20",
    "action": "Over-Levered",
    "exchange_name": "NASDAQ",
    "return": 34.054054,
    "class_action": "No",
    "auditor_resigned": "No",
    "full_report": "No",
    "delisted": "No",
    "company_respnd": "Yes",
    "current_status": "Current",
    "price_per_share": null,
    "Purchase_Value_mn": null,
    "currency": "",
    "buyer": "",
    "activist_founded": 2019,
    "market_cap_USD": 294.534921,
    "industry_name": "Internet Content & Information",
    "industry_sector_name": "Technology",
    "country": "US",
    "Year_action": 2020,
    "company_region": "North America",
    "market_cap_category": "Small-Cap",
    "activist_HQ": "US",
    "exit_date": "11-May-21",
    "Downside_Target": 100
  },
  {
    "activist_id": 2738,
    "investor_id": 5486,
    "PID": 2039,
    "activist_name": "Hindenburg Research",
    "campaign_summary_id": 30686,
    "company_id": 20027,
    "company_name": "Park National Corporation",
    "symbol": "PRK",
    "action_date": "03-Aug-20",
    "action": "Other Overvaluation",
    "exchange_name": "NYSE MKT",
    "return": -5.958489,
    "class_action": "No",
    "auditor_resigned": "No",
    "full_report": "No",
    "delisted": "No",
    "company_respnd": "No",
    "current_status": "Current",
    "price_per_share": null,
    "Purchase_Value_mn": null,
    "currency": "",
    "buyer": "",
    "activist_founded": 2017,
    "market_cap_USD": 2059.014803,
    "industry_name": "Banks - Regional - US",
    "industry_sector_name": "Financial Services",
    "country": "US",
    "Year_action": 2020,
    "company_region": "North America",
    "market_cap_category": "Mid-Cap",
    "activist_HQ": "US",
    "exit_date": "11-May-21",
    "Downside_Target": 17.0384
  },
  {
    "activist_id": 1269,
    "investor_id": 6517,
    "PID": 4916,
    "activist_name": "White Diamond Research",
    "campaign_summary_id": 30688,
    "company_id": 7943,
    "company_name": "Microvision Inc.",
    "symbol": "MVIS",
    "action_date": "03-Aug-20",
    "action": "Other Overvaluation",
    "exchange_name": "NASDAQ",
    "return": 12.376238,
    "class_action": "No",
    "auditor_resigned": "No",
    "full_report": "Yes",
    "delisted": "No",
    "company_respnd": "No",
    "current_status": "Current",
    "price_per_share": null,
    "Purchase_Value_mn": null,
    "currency": "",
    "buyer": "",
    "activist_founded": 2009,
    "market_cap_USD": 2370.311682,
    "industry_name": "Electronic Components",
    "industry_sector_name": "Technology",
    "country": "US",
    "Year_action": 2020,
    "company_region": "North America",
    "market_cap_category": "Mid-Cap",
    "activist_HQ": "US",
    "exit_date": "11-May-21",
    "Downside_Target": 92.5
  },
  {
    "activist_id": 4084,
    "investor_id": 9288,
    "PID": 37351,
    "activist_name": "Mariner Research",
    "campaign_summary_id": 30607,
    "company_id": 20005,
    "company_name": "Timbercreek Financial Corp",
    "symbol": "TF.TO",
    "action_date": "28-Jul-20",
    "action": "Over-Levered, Misleading Accounting",
    "exchange_name": "Toronto Stock Exchange",
    "return": -1.254438,
    "class_action": "No",
    "auditor_resigned": "No",
    "full_report": "Yes",
    "delisted": "No",
    "company_respnd": "No",
    "current_status": "Current",
    "price_per_share": null,
    "Purchase_Value_mn": null,
    "currency": "",
    "buyer": "",
    "activist_founded": null,
    "market_cap_USD": 559.085299,
    "industry_name": "Real Estate - General",
    "industry_sector_name": "Real Estate",
    "country": "Canada",
    "Year_action": 2020,
    "company_region": "North America",
    "market_cap_category": "Small-Cap",
    "activist_HQ": null,
    "exit_date": "11-May-21",
    "Downside_Target": 52.6627
  },
  {
    "activist_id": 2738,
    "investor_id": 5486,
    "PID": 49413,
    "activist_name": "Hindenburg Research",
    "campaign_summary_id": 30550,
    "company_id": 19984,
    "company_name": "Facedrive Inc.",
    "symbol": "FD.V",
    "action_date": "23-Jul-20",
    "action": "Stock Promotion",
    "exchange_name": "TSX Venture Exchange",
    "return": 3.846154,
    "class_action": "No",
    "auditor_resigned": "No",
    "full_report": "Yes",
    "delisted": "No",
    "company_respnd": "No",
    "current_status": "Current",
    "price_per_share": null,
    "Purchase_Value_mn": null,
    "currency": "",
    "buyer": "",
    "activist_founded": 2017,
    "market_cap_USD": 3367.33798,
    "industry_name": "Software - Application",
    "industry_sector_name": "Technology",
    "country": "Canada",
    "Year_action": 2020,
    "company_region": "North America",
    "market_cap_category": "Mid-Cap",
    "activist_HQ": "US",
    "exit_date": "11-May-21",
    "Downside_Target": 95.046
  }
]
